drf_auth_jwt/__init__.py
drf_auth_jwt/admin.py
drf_auth_jwt/apps.py
drf_auth_jwt/serializers.py
drf_auth_jwt/tests.py
drf_auth_jwt/urls.py
drf_auth_jwt/utils.py
drf_auth_jwt/views.py
drf_auth_jwt_cu/__init__.py
drf_auth_jwt_cu/admin.py
drf_auth_jwt_cu/apps.py
drf_auth_jwt_cu/models.py
drf_auth_jwt_cu/serializers.py
drf_auth_jwt_cu/tests.py
drf_auth_jwt_cu/urls.py
drf_auth_jwt_cu/utils.py
drf_auth_jwt_cu/views.py
drf_auth_knox/__init__.py
drf_auth_knox/admin.py
drf_auth_knox/apps.py
drf_auth_knox/serializers.py
drf_auth_knox/tests.py
drf_auth_knox/urls.py
drf_auth_knox/utils.py
drf_auth_knox/views.py
drf_auth_knox_cu/__init__.py
drf_auth_knox_cu/admin.py
drf_auth_knox_cu/apps.py
drf_auth_knox_cu/models.py
drf_auth_knox_cu/serializers.py
drf_auth_knox_cu/tests.py
drf_auth_knox_cu/urls.py
drf_auth_knox_cu/utils.py
drf_auth_knox_cu/views.py
drf_auth_simple-1.0.4.dist-info/LICENSE
drf_auth_simple-1.0.4.dist-info/METADATA
drf_auth_simple-1.0.4.dist-info/WHEEL
drf_auth_simple-1.0.4.dist-info/top_level.txt
drf_auth_simple-1.0.4.dist-info/RECORD
