Metadata-Version: 2.1
Name: drf-auth-simple
Version: 1.0.4
Summary: For drf simple authentication with custom user model
Home-page: https://github.com/degerahmet/drf-authentication
Author: Ahmet Deger
Author-email: adeger@protonmail.com
License: Apache Software License
Platform: UNKNOWN
Classifier: Programming Language :: Python :: 3
Classifier: License :: OSI Approved :: Apache Software License
Classifier: Operating System :: OS Independent
Requires-Python: >=3.5
License-File: LICENSE
Requires-Dist: django-rest-knox
Requires-Dist: djangorestframework-simplejwt
Requires-Dist: boto3
Requires-Dist: jwt
Requires-Dist: PyJWT (>=2.3.0)
Requires-Dist: datetime
